[
  {
    "beginString" : "^([\\t ]*)(\\w[\\w\\s]*)\\s+(\\**\\w+)\\(([\\s\\w*&,\\[\\]]*)\\)[\\t ]*(?=\\{|//|$)",
    "description" : "function",
    "keyString" : "$1 $3($4)",
    "kind" : "function"
  },
  {
    "beginString" : "^enum[\\t ]+(\\w+)",
    "description" : "enum",
    "keyString" : "enum $1",
    "kind" : "container"
  },
  {
    "beginString" : "^struct[\\t ]+(\\w+)",
    "description" : "struct",
    "keyString" : "struct $1",
    "kind" : "container"
  },
  {
    "beginString" : "^union[\\t ]+(\\w+)",
    "description" : "union",
    "keyString" : "union $1",
    "kind" : "container"
  }
]