{
  "comment" : {
    "blocks" : [

    ],
    "inlines" : [
      {
        "begin" : "#"
      }
    ]
  },
  "stringDelimiters" : [
    {
      "begin" : "\"",
      "end" : "\""
    },
    {
      "begin" : "\"\"\"",
      "end" : "\"\"\"",
      "isMultiline" : true
    },
    {
      "begin" : "'",
      "end" : "'"
    },
    {
      "begin" : "'''",
      "end" : "'''",
      "isMultiline" : true
    },
    {
      "begin" : "`",
      "end" : "`"
    }
  ],
  "indentation" : {
    "blockDelimiters" : [
      {
        "begin" : ":"
      }
    ]
  }
}